anyconfig/__init__.py
anyconfig/dicts.py
anyconfig/parser.py
anyconfig/singleton.py
anyconfig/api/__init__.py
anyconfig/api/_dump.py
anyconfig/api/_load.py
anyconfig/api/_open.py
anyconfig/api/datatypes.py
anyconfig/api/utils.py
anyconfig/backend/__init__.py
anyconfig/backend/ini.py
anyconfig/backend/pickle.py
anyconfig/backend/properties.py
anyconfig/backend/shellvars.py
anyconfig/backend/toml.py
anyconfig/backend/xml.py
anyconfig/backend/base/__init__.py
anyconfig/backend/base/compat.py
anyconfig/backend/base/datatypes.py
anyconfig/backend/base/dumpers.py
anyconfig/backend/base/loaders.py
anyconfig/backend/base/parsers.py
anyconfig/backend/base/utils.py
anyconfig/backend/json/__init__.py
anyconfig/backend/json/common.py
anyconfig/backend/json/default.py
anyconfig/backend/json/simplejson.py
anyconfig/backend/yaml/__init__.py
anyconfig/backend/yaml/common.py
anyconfig/backend/yaml/pyyaml.py
anyconfig/backend/yaml/ruamel_yaml.py
anyconfig/cli/__init__.py
anyconfig/cli/_main.py
anyconfig/cli/actions.py
anyconfig/cli/constants.py
anyconfig/cli/detectors.py
anyconfig/cli/filters.py
anyconfig/cli/io.py
anyconfig/cli/parse_args.py
anyconfig/cli/utils.py
anyconfig/common/__init__.py
anyconfig/common/datatypes.py
anyconfig/common/errors.py
anyconfig/ioinfo/__init__.py
anyconfig/ioinfo/constants.py
anyconfig/ioinfo/datatypes.py
anyconfig/ioinfo/detectors.py
anyconfig/ioinfo/factory.py
anyconfig/ioinfo/utils.py
anyconfig/models/__init__.py
anyconfig/models/processor.py
anyconfig/parsers/__init__.py
anyconfig/parsers/parsers.py
anyconfig/parsers/utils.py
anyconfig/processors/__init__.py
anyconfig/processors/datatypes.py
anyconfig/processors/processors.py
anyconfig/processors/utils.py
anyconfig/query/__init__.py
anyconfig/query/datatypes.py
anyconfig/query/default.py
anyconfig/query/query.py
anyconfig/schema/__init__.py
anyconfig/schema/datatypes.py
anyconfig/schema/default.py
anyconfig/schema/jsonschema.py
anyconfig/template/__init__.py
anyconfig/template/jinja2.py
anyconfig-0.12.0.dist-info/AUTHORS.txt
anyconfig-0.12.0.dist-info/LICENSE.MIT
anyconfig-0.12.0.dist-info/METADATA
anyconfig-0.12.0.dist-info/WHEEL
anyconfig-0.12.0.dist-info/entry_points.txt
anyconfig-0.12.0.dist-info/top_level.txt
anyconfig-0.12.0.dist-info/RECORD
